{
  "type": "join",
  "neverRecomputeExistingPartitions": false,
  "optionalDependencies": false,
  "customMeta": {
    "kv": {}
  },
  "redispatchPartitioning": false,
  "maxRunningActivities": 0,
  "inputs": {
    "main": {
      "items": [
        {
          "ref": "Basketball_Experience_by_Player",
          "deps": []
        },
        {
          "ref": "Basketball_Experience",
          "deps": []
        }
      ]
    }
  },
  "outputs": {
    "main": {
      "items": [
        {
          "ref": "Basketball_EXP_TM",
          "appendMode": false
        }
      ]
    }
  },
  "versionTag": {
    "versionNumber": 4,
    "lastModifiedBy": {
      "login": "admin"
    },
    "lastModifiedOn": 1541192984150
  },
  "creationTag": {
    "versionNumber": 0,
    "lastModifiedBy": {
      "login": "admin"
    },
    "lastModifiedOn": 1541190447544
  },
  "tags": [],
  "customFields": {},
  "checklists": {
    "checklists": []
  }
}